<?xml version="1.0" encoding="utf-8"?>
	<single_run excl="define Hp = H+ H- " process="generate  p p &gt; Hpp Hp /EXCL">
		<parameters>
			<parameter name="mHpp" value="200"/>
			<parameter name="mHp" value="200"/>
			<parameter name="mha" value="200.995"/>
			<parameter name="mh__2" value="200.995"/>
			<parameter name="mh" value="200.995"/>
			<parameter name="vt" value=""/>
			<parameter name="sinalpha" value="1e-05"/>
			<parameter name="mu" value="0.0944095"/>
			<parameter name="lam1" value="1.29871"/>
			<parameter name="lam2" value="4.99871"/>
			<parameter name="lam3" value="-4.10108"/>
			<parameter name="lam4" value="0.026375"/>
		</parameters>
		<cross_section>
			<xsec_central_value value="0.1144"/>
			<xsec_central_error value="0.0002032"/>
		</cross_section>
		<DECAY>
			<BSM_HIGGS particle="H+" width="4.634621e-07">
				<decay branch_ratio="2.210100e-11" final_state="e+_ve"/>
				<decay branch_ratio="1.232336e-04" final_state="ta+_vm"/>
				<decay branch_ratio="4.109766e-01" final_state="b~_t"/>
				<decay branch_ratio="1.044924e-05" final_state="b~_c"/>
				<decay branch_ratio="1.228320e-05" final_state="d~_t"/>
				<decay branch_ratio="2.545772e-05" final_state="ta+_ve"/>
				<decay branch_ratio="5.006834e-07" final_state="mu+_vt"/>
				<decay branch_ratio="1.375091e-07" final_state="s~_u"/>
				<decay branch_ratio="6.595367e-04" final_state="s~_t"/>
				<decay branch_ratio="1.170063e-11" final_state="e+_vm"/>
				<decay branch_ratio="5.876028e-01" final_state="z_w+"/>
				<decay branch_ratio="7.455371e-08" final_state="b~_u"/>
				<decay branch_ratio="2.374596e-07" final_state="mu+_ve"/>
				<decay branch_ratio="8.370033e-09" final_state="d~_u"/>
				<decay branch_ratio="1.415877e-04" final_state="ta+_vt"/>
				<decay branch_ratio="1.786577e-12" final_state="e+_vt"/>
				<decay branch_ratio="4.250819e-04" final_state="s~_c"/>
				<decay branch_ratio="2.883249e-07" final_state="mu+_vm"/>
				<decay branch_ratio="2.171886e-05" final_state="d~_c"/>
			</BSM_HIGGS>
			<BSM_HIGGS particle="H++" width="6.962315e-07">
				<decay branch_ratio="3.600353e-12" final_state="ta+_mu+"/>
				<decay branch_ratio="1.937120e-11" final_state="ta+_ta+"/>
				<decay branch_ratio="7.638627e-13" final_state="mu+_e+"/>
				<decay branch_ratio="7.261104e-15" final_state="ta+_e+"/>
				<decay branch_ratio="7.448355e-12" final_state="e+_e+"/>
				<decay branch_ratio="1.829304e-11" final_state="mu+_mu+"/>
				<decay branch_ratio="1.000000e+00" final_state="w+_w+"/>
			</BSM_HIGGS>
			<BSM_HIGGS particle="H--" width="6.962315e-07">
				<decay branch_ratio="3.600353e-12" final_state="ta-_mu-"/>
				<decay branch_ratio="7.261104e-15" final_state="ta-_e-"/>
				<decay branch_ratio="7.448355e-12" final_state="e-_e-"/>
				<decay branch_ratio="7.638627e-13" final_state="mu-_e-"/>
				<decay branch_ratio="1.937120e-11" final_state="ta-_ta-"/>
				<decay branch_ratio="1.000000e+00" final_state="w-_w-"/>
				<decay branch_ratio="1.829304e-11" final_state="mu-_mu-"/>
			</BSM_HIGGS>
			<BSM_HIGGS particle="H-" width="4.634621e-07">
				<decay branch_ratio="7.455371e-08" final_state="b_u~"/>
				<decay branch_ratio="4.109766e-01" final_state="b_t~"/>
				<decay branch_ratio="1.228320e-05" final_state="d_t~"/>
				<decay branch_ratio="2.171886e-05" final_state="d_c~"/>
				<decay branch_ratio="5.006834e-07" final_state="mu-_vt"/>
				<decay branch_ratio="4.250819e-04" final_state="s_c~"/>
				<decay branch_ratio="2.374596e-07" final_state="mu-_ve"/>
				<decay branch_ratio="8.370033e-09" final_state="d_u~"/>
				<decay branch_ratio="2.883249e-07" final_state="mu-_vm"/>
				<decay branch_ratio="1.170063e-11" final_state="e-_vm"/>
				<decay branch_ratio="6.595367e-04" final_state="s_t~"/>
				<decay branch_ratio="1.786577e-12" final_state="e-_vt"/>
				<decay branch_ratio="5.876028e-01" final_state="z_w-"/>
				<decay branch_ratio="1.044924e-05" final_state="b_c~"/>
				<decay branch_ratio="2.210100e-11" final_state="e-_ve"/>
				<decay branch_ratio="2.545772e-05" final_state="ta-_ve"/>
				<decay branch_ratio="1.375091e-07" final_state="s_u~"/>
				<decay branch_ratio="1.415877e-04" final_state="ta-_vt"/>
				<decay branch_ratio="1.232336e-04" final_state="ta-_vm"/>
			</BSM_HIGGS>
		</DECAY>
	</single_run>
